lois/__init__.py
lois/main.py
tests/__init__.py
lois-0.5.0.dist-info/LICENSE.txt
lois-0.5.0.dist-info/METADATA
lois-0.5.0.dist-info/WHEEL
lois-0.5.0.dist-info/top_level.txt
lois-0.5.0.dist-info/RECORD
