Metadata-Version: 2.1
Name: lois
Version: 0.5.0
Summary: the fastest and easy way to get insight of your dataset
Home-page: https://github.com/charleslf2/lois.git
Author: Charles TCHANAKE
Author-email: datadevfernolf@gmail.com
License: MIT
Project-URL: Bug Tracker, https://github.com/charleslf2/lois/issues
Keywords: EDA,Data analysis,Charles TCHANAKE,Automation
Classifier: License :: OSI Approved :: MIT License
Classifier: Programming Language :: Python :: 3
Classifier: Operating System :: OS Independent
License-File: LICENSE.txt
Requires-Dist: pandas
Requires-Dist: matplotlib
Requires-Dist: seaborn
Requires-Dist: rich
